maven_check_versions/__init__.py
maven_check_versions/__main__.py
maven_check_versions/cache.py
maven_check_versions/config.py
maven_check_versions/cveutils.py
maven_check_versions/logutils.py
maven_check_versions/process.py
maven_check_versions/utils.py
maven_check_versions-0.8.1.dist-info/licenses/LICENSE
maven_check_versions-0.8.1.dist-info/METADATA
maven_check_versions-0.8.1.dist-info/WHEEL
maven_check_versions-0.8.1.dist-info/entry_points.txt
maven_check_versions-0.8.1.dist-info/top_level.txt
maven_check_versions-0.8.1.dist-info/RECORD
