Metadata-Version: 2.4
Name: maven_check_versions
Version: 0.8.1
Summary: Maven check versions package
Author: Alexander Bulgakov
License: MIT License
Project-URL: Homepage, https://github.com/alexundros/maven-check-versions
Project-URL: Issues, https://github.com/alexundros/maven-check-versions/issues
Project-URL: Source, https://github.com/alexundros/maven-check-versions
Classifier: Topic :: Software Development :: Build Tools
Classifier: Programming Language :: Python :: 3.10
Classifier: Programming Language :: Python :: 3.11
Classifier: Programming Language :: Python :: 3.12
Classifier: Programming Language :: Python :: 3.13
Classifier: License :: OSI Approved :: MIT License
Classifier: Operating System :: OS Independent
Requires-Python: >=3.10
License-File: LICENSE
Requires-Dist: requests
Requires-Dist: beautifulsoup4
Requires-Dist: python-dateutil
Requires-Dist: pyyaml
Requires-Dist: redis
Requires-Dist: tarantool
Requires-Dist: pymemcache
Dynamic: license-file
